{
	"configurations" : 
	[
		{
			"directories" : 
			[
				{
					"build" : ".",
					"jsonFile" : "directory-.-Debug-f5ebdc15457944623624.json",
					"minimumCMakeVersion" : 
					{
						"string" : "3.23"
					},
					"projectIndex" : 0,
					"source" : ".",
					"targetIndexes" : 
					[
						0
					]
				}
			],
			"name" : "Debug",
			"projects" : 
			[
				{
					"directoryIndexes" : 
					[
						0
					],
					"name" : "1476",
					"targetIndexes" : 
					[
						0
					]
				}
			],
			"targets" : 
			[
				{
					"directoryIndex" : 0,
					"id" : "1476::@6890427a1f51a3e7e1df",
					"jsonFile" : "target-1476-Debug-5c5516e896efd36c4b1b.json",
					"name" : "1476",
					"projectIndex" : 0
				}
			]
		}
	],
	"kind" : "codemodel",
	"paths" : 
	{
		"build" : "/Users/kimjaewoo/Desktop/C++/\uc54c\uace0\ub9ac\uc998 \uae30\ucd08 \ube0c\ub8e8\ud2b8\ud3ec\uc2a4/1476/cmake-build-debug",
		"source" : "/Users/kimjaewoo/Desktop/C++/\uc54c\uace0\ub9ac\uc998 \uae30\ucd08 \ube0c\ub8e8\ud2b8\ud3ec\uc2a4/1476"
	},
	"version" : 
	{
		"major" : 2,
		"minor" : 4
	}
}
